nobrainerzoo/__init__.py
nobrainerzoo/_version.py
nobrainerzoo/cli.py
nobrainerzoo/download.py
nobrainerzoo/utils.py
nobrainer_zoo-0.2.0.dist-info/LICENSE
nobrainer_zoo-0.2.0.dist-info/METADATA
nobrainer_zoo-0.2.0.dist-info/WHEEL
nobrainer_zoo-0.2.0.dist-info/entry_points.txt
nobrainer_zoo-0.2.0.dist-info/top_level.txt
nobrainer_zoo-0.2.0.dist-info/RECORD
