Metadata-Version: 2.1
Name: nobrainer-zoo
Version: 0.2.0
Summary: A framework for inference and re-training of pretrained neuroimaging models
Home-page: https://neuronets.github.io
Author: Nobrainer Developers
Author-email: rajaei.hoda@gmail.com
License: Apache License, 2.0
Project-URL: Source Code, https://github.com/neuronets/nobrainer-zoo
Keywords: neuroimaging,model-zoo,medical-imaging,deeplearning
Classifier: Development Status :: 3 - Alpha
Classifier: Environment :: Console
Classifier: Intended Audience :: Developers
Classifier: Intended Audience :: Education
Classifier: Intended Audience :: Healthcare Industry
Classifier: Intended Audience :: Science/Research
Classifier: License :: OSI Approved :: Apache Software License
Classifier: Operating System :: OS Independent
Classifier: Programming Language :: Python :: 3
Classifier: Programming Language :: Python :: 3 :: Only
Classifier: Programming Language :: Python :: 3.7
Classifier: Programming Language :: Python :: 3.8
Classifier: Programming Language :: Python :: 3.9
Classifier: Programming Language :: Python :: 3.10
Classifier: Topic :: Scientific/Engineering :: Artificial Intelligence
Classifier: Topic :: Software Development
Classifier: Topic :: Software Development :: Libraries :: Python Modules
Requires-Python: >=3.7
License-File: LICENSE
Requires-Dist: click
Requires-Dist: pyyaml
Provides-Extra: dev
Requires-Dist: nobrainer ; extra == 'dev'
